[
  {
    "timestamp": "2025-06-26T14:59:17.056814+00:00",
    "miner_uid": "c12f18f7-0c8b-4d8b-9040-7c1a47ad163f",
    "status": "active",
    "compute_score": 0.064,
    "uptime_reward": 0.0,
    "block_number": 5866068,
    "reason": "Initial uptime log"
  },
  {
    "timestamp": "2025-06-26T14:59:17.059138+00:00",
    "miner_uid": "c12f18f7-0c8b-4d8b-9040-7c1a47ad163f",
    "status": "active",
    "compute_score": 0.064,
    "uptime_reward": 1.2800000000000003e-05,
    "block_number": 5866068,
    "reason": "Reward updated"
  },
  {
    "timestamp": "2025-06-26T15:45:29.636713+00:00",
    "miner_uid": "c12f18f7-0c8b-4d8b-9040-7c1a47ad163f",
    "status": "active",
    "compute_score": 0.064,
    "uptime_reward": 0.0,
    "block_number": 5866337,
    "reason": "Initial uptime log"
  },
  {
    "timestamp": "2025-06-26T15:45:29.638377+00:00",
    "miner_uid": "c12f18f7-0c8b-4d8b-9040-7c1a47ad163f",
    "status": "active",
    "compute_score": 0.064,
    "uptime_reward": 1.2800000000000003e-05,
    "block_number": 5866337,
    "reason": "Reward updated"
  },
  {
    "timestamp": "2025-06-26T16:19:48.939342+00:00",
    "miner_uid": "c12f18f7-0c8b-4d8b-9040-7c1a47ad163f",
    "status": "active",
    "compute_score": 0.063,
    "uptime_reward": 0.0,
    "block_number": 5866574,
    "reason": "Initial uptime log"
  },
  {
    "timestamp": "2025-06-26T16:19:48.942198+00:00",
    "miner_uid": "c12f18f7-0c8b-4d8b-9040-7c1a47ad163f",
    "status": "active",
    "compute_score": 0.063,
    "uptime_reward": 1.2600000000000003e-05,
    "block_number": 5866574,
    "reason": "Reward updated"
  },
  {
    "timestamp": "2025-06-26T17:00:48.982992+00:00",
    "miner_uid": "c12f18f7-0c8b-4d8b-9040-7c1a47ad163f",
    "status": "active",
    "compute_score": 0.063,
    "uptime_reward": 0.0,
    "block_number": 5866765,
    "reason": "Initial uptime log"
  },
  {
    "timestamp": "2025-06-26T17:00:48.987975+00:00",
    "miner_uid": "c12f18f7-0c8b-4d8b-9040-7c1a47ad163f",
    "status": "active",
    "compute_score": 0.063,
    "uptime_reward": 1.2600000000000003e-05,
    "block_number": 5866765,
    "reason": "Reward updated"
  },
  {
    "timestamp": "2025-06-27T09:36:14.453506+00:00",
    "miner_uid": "c12f18f7-0c8b-4d8b-9040-7c1a47ad163f",
    "status": "active",
    "compute_score": 0.064,
    "uptime_reward": 0.0,
    "block_number": 5871668,
    "reason": "Initial uptime log"
  },
  {
    "timestamp": "2025-06-27T09:36:14.455163+00:00",
    "miner_uid": "c12f18f7-0c8b-4d8b-9040-7c1a47ad163f",
    "status": "active",
    "compute_score": 0.064,
    "uptime_reward": 1.2800000000000003e-05,
    "block_number": 5871668,
    "reason": "Reward updated"
  }
]