[
  {
    "timestamp": "2025-06-26T14:59:21.954801+00:00",
    "miner_uid": "78ef5471-a82d-426d-a2f4-01c299a7bf3d",
    "status": "active",
    "compute_score": 0.041,
    "uptime_reward": 0.0,
    "block_number": 5866068,
    "reason": "Initial uptime log"
  },
  {
    "timestamp": "2025-06-26T14:59:21.956730+00:00",
    "miner_uid": "78ef5471-a82d-426d-a2f4-01c299a7bf3d",
    "status": "active",
    "compute_score": 0.041,
    "uptime_reward": 8.200000000000001e-06,
    "block_number": 5866068,
    "reason": "Reward updated"
  },
  {
    "timestamp": "2025-06-26T15:45:33.269713+00:00",
    "miner_uid": "78ef5471-a82d-426d-a2f4-01c299a7bf3d",
    "status": "active",
    "compute_score": 0.041,
    "uptime_reward": 0.0,
    "block_number": 5866337,
    "reason": "Initial uptime log"
  },
  {
    "timestamp": "2025-06-26T15:45:33.271296+00:00",
    "miner_uid": "78ef5471-a82d-426d-a2f4-01c299a7bf3d",
    "status": "active",
    "compute_score": 0.041,
    "uptime_reward": 8.200000000000001e-06,
    "block_number": 5866337,
    "reason": "Reward updated"
  },
  {
    "timestamp": "2025-06-26T16:19:50.384316+00:00",
    "miner_uid": "78ef5471-a82d-426d-a2f4-01c299a7bf3d",
    "status": "active",
    "compute_score": 0.041,
    "uptime_reward": 0.0,
    "block_number": 5866574,
    "reason": "Initial uptime log"
  },
  {
    "timestamp": "2025-06-26T16:19:50.385884+00:00",
    "miner_uid": "78ef5471-a82d-426d-a2f4-01c299a7bf3d",
    "status": "active",
    "compute_score": 0.041,
    "uptime_reward": 8.200000000000001e-06,
    "block_number": 5866574,
    "reason": "Reward updated"
  },
  {
    "timestamp": "2025-06-26T17:00:51.639136+00:00",
    "miner_uid": "78ef5471-a82d-426d-a2f4-01c299a7bf3d",
    "status": "active",
    "compute_score": 0.041,
    "uptime_reward": 0.0,
    "block_number": 5866765,
    "reason": "Initial uptime log"
  },
  {
    "timestamp": "2025-06-26T17:00:51.640725+00:00",
    "miner_uid": "78ef5471-a82d-426d-a2f4-01c299a7bf3d",
    "status": "active",
    "compute_score": 0.041,
    "uptime_reward": 8.200000000000001e-06,
    "block_number": 5866765,
    "reason": "Reward updated"
  },
  {
    "timestamp": "2025-06-27T09:36:18.632333+00:00",
    "miner_uid": "78ef5471-a82d-426d-a2f4-01c299a7bf3d",
    "status": "active",
    "compute_score": 0.041,
    "uptime_reward": 0.0,
    "block_number": 5871668,
    "reason": "Initial uptime log"
  },
  {
    "timestamp": "2025-06-27T09:36:18.634264+00:00",
    "miner_uid": "78ef5471-a82d-426d-a2f4-01c299a7bf3d",
    "status": "active",
    "compute_score": 0.041,
    "uptime_reward": 8.200000000000001e-06,
    "block_number": 5871668,
    "reason": "Reward updated"
  }
]