[
  {
    "timestamp": "2025-06-26T14:59:22.058679+00:00",
    "miner_uid": "2ad6c2a1-1692-4fd3-8148-a3990370f7fe",
    "status": "active",
    "compute_score": 0.078,
    "uptime_reward": 0.0,
    "block_number": 5866068,
    "reason": "Initial uptime log"
  },
  {
    "timestamp": "2025-06-26T14:59:22.059823+00:00",
    "miner_uid": "2ad6c2a1-1692-4fd3-8148-a3990370f7fe",
    "status": "active",
    "compute_score": 0.078,
    "uptime_reward": 1.5600000000000003e-05,
    "block_number": 5866068,
    "reason": "Reward updated"
  },
  {
    "timestamp": "2025-06-26T15:45:33.394745+00:00",
    "miner_uid": "2ad6c2a1-1692-4fd3-8148-a3990370f7fe",
    "status": "active",
    "compute_score": 0.078,
    "uptime_reward": 0.0,
    "block_number": 5866337,
    "reason": "Initial uptime log"
  },
  {
    "timestamp": "2025-06-26T15:45:33.396289+00:00",
    "miner_uid": "2ad6c2a1-1692-4fd3-8148-a3990370f7fe",
    "status": "active",
    "compute_score": 0.078,
    "uptime_reward": 1.5600000000000003e-05,
    "block_number": 5866337,
    "reason": "Reward updated"
  },
  {
    "timestamp": "2025-06-26T16:19:50.454315+00:00",
    "miner_uid": "2ad6c2a1-1692-4fd3-8148-a3990370f7fe",
    "status": "active",
    "compute_score": 0.078,
    "uptime_reward": 0.0,
    "block_number": 5866574,
    "reason": "Initial uptime log"
  },
  {
    "timestamp": "2025-06-26T16:19:50.455470+00:00",
    "miner_uid": "2ad6c2a1-1692-4fd3-8148-a3990370f7fe",
    "status": "active",
    "compute_score": 0.078,
    "uptime_reward": 1.5600000000000003e-05,
    "block_number": 5866574,
    "reason": "Reward updated"
  },
  {
    "timestamp": "2025-06-26T17:00:51.785587+00:00",
    "miner_uid": "2ad6c2a1-1692-4fd3-8148-a3990370f7fe",
    "status": "active",
    "compute_score": 0.079,
    "uptime_reward": 0.0,
    "block_number": 5866765,
    "reason": "Initial uptime log"
  },
  {
    "timestamp": "2025-06-26T17:00:51.787139+00:00",
    "miner_uid": "2ad6c2a1-1692-4fd3-8148-a3990370f7fe",
    "status": "active",
    "compute_score": 0.079,
    "uptime_reward": 1.5800000000000005e-05,
    "block_number": 5866765,
    "reason": "Reward updated"
  },
  {
    "timestamp": "2025-06-27T09:36:19.136249+00:00",
    "miner_uid": "2ad6c2a1-1692-4fd3-8148-a3990370f7fe",
    "status": "active",
    "compute_score": 0.079,
    "uptime_reward": 0.0,
    "block_number": 5871668,
    "reason": "Initial uptime log"
  },
  {
    "timestamp": "2025-06-27T09:36:19.137915+00:00",
    "miner_uid": "2ad6c2a1-1692-4fd3-8148-a3990370f7fe",
    "status": "active",
    "compute_score": 0.079,
    "uptime_reward": 1.5800000000000005e-05,
    "block_number": 5871668,
    "reason": "Reward updated"
  }
]